odoo10_addon_stock_account_quant_merge-10.0.1.0.1-py3.8-nspkg.pth
odoo/addons/stock_account_quant_merge/README.rst
odoo/addons/stock_account_quant_merge/__init__.py
odoo/addons/stock_account_quant_merge/__manifest__.py
odoo/addons/stock_account_quant_merge/i18n/de.po
odoo/addons/stock_account_quant_merge/i18n/es.po
odoo/addons/stock_account_quant_merge/i18n/fi.po
odoo/addons/stock_account_quant_merge/i18n/fr.po
odoo/addons/stock_account_quant_merge/i18n/it.po
odoo/addons/stock_account_quant_merge/i18n/pt_BR.po
odoo/addons/stock_account_quant_merge/i18n/ro.po
odoo/addons/stock_account_quant_merge/i18n/sl.po
odoo/addons/stock_account_quant_merge/i18n/stock_account_quant_merge.pot
odoo/addons/stock_account_quant_merge/models/__init__.py
odoo/addons/stock_account_quant_merge/models/stock.py
odoo/addons/stock_account_quant_merge/static/description/icon.png
odoo/addons/stock_account_quant_merge/tests/__init__.py
odoo/addons/stock_account_quant_merge/tests/test_merge.py
odoo10_addon_stock_account_quant_merge-10.0.1.0.1.dist-info/METADATA
odoo10_addon_stock_account_quant_merge-10.0.1.0.1.dist-info/WHEEL
odoo10_addon_stock_account_quant_merge-10.0.1.0.1.dist-info/namespace_packages.txt
odoo10_addon_stock_account_quant_merge-10.0.1.0.1.dist-info/top_level.txt
odoo10_addon_stock_account_quant_merge-10.0.1.0.1.dist-info/RECORD
